Workbook

Sheet store_performance
A1: store_id | B1: month | C1: store_type | D1: region | E1: South Dummy | F1: East Dummy | G1: West Dummy | H1: marketing_spend | I1: footfall | J1: avg_discount_pct | K1: staff_count | L1: inventory_availability_pct | M1: competitor_distance_km | N1: holiday_flag | O1: customer_rating | P1: monthly_sales | Q1: monthly_profit
A2: STR-1001 | B2: 45658 | C2: Residential | D2: East | E2: =IF(D2="South",1,0) -> 0 | F2: =IF(D2="East",1,0) -> 1 | G2: =IF(D2="West",1,0) -> 0 | H2: 70389.11 | I2: 8302 | J2: 0.042 | K2: 17 | L2: 75 | M2: 5.28 | N2: 1 | O2: 3.1 | P2: 658832.62 | Q2: 84349.93
A3: STR-1001 | B3: 45689 | C3: Residential | D3: East | E3: =IF(D3="South",1,0) -> 0 | F3: =IF(D3="East",1,0) -> 1 | G3: =IF(D3="West",1,0) -> 0 | H3: 43827.89 | I3: 8487 | J3: 0.168 | K3: 23 | L3: 84.4 | M3: 4.31 | N3: 0 | O3: 2.8 | P3: 634436 | Q3: 106130.54
A4: STR-1001 | B4: 45717 | C4: Residential | D4: East | E4: =IF(D4="South",1,0) -> 0 | F4: =IF(D4="East",1,0) -> 1 | G4: =IF(D4="West",1,0) -> 0 | H4: 59921.75 | I4: 9113 | J4: 0.133 | K4: 20 | L4: 88 | M4: 12 | N4: 0 | O4: 3.2 | P4: 678722.06 | Q4: 101883.86
A5: STR-1001 | B5: 45748 | C5: Residential | D5: East | E5: =IF(D5="South",1,0) -> 0 | F5: =IF(D5="East",1,0) -> 1 | G5: =IF(D5="West",1,0) -> 0 | H5: 56856.63 | I5: 9431 | J5: 0.142 | K5: 23 | L5: 86.9 | M5: 4.97 | N5: 0 | O5: 3.4 | P5: 658920.3 | Q5: 97910.37
A6: STR-1002 | B6: 45658 | C6: High Street | D6: East | E6: =IF(D6="South",1,0) -> 0 | F6: =IF(D6="East",1,0) -> 1 | G6: =IF(D6="West",1,0) -> 0 | H6: 48412.64 | I6: 9545 | J6: 0.231 | K6: 21 | L6: 97.6 | M6: 6.94 | N6: 1 | O6: 4.2 | P6: 741341.44 | Q6: 119208.17
A7: STR-1002 | B7: 45689 | C7: High Street | D7: East | E7: =IF(D7="South",1,0) -> 0 | F7: =IF(D7="East",1,0) -> 1 | G7: =IF(D7="West",1,0) -> 0 | H7: 64811.21 | I7: 9792 | J7: 0.112 | K7: 20 | L7: 84.2 | M7: 2.88 | N7: 0 | O7: 4.2 | P7: 761835.34 | Q7: 149602.23
A8: STR-1002 | B8: 45717 | C8: High Street | D8: East | E8: =IF(D8="South",1,0) -> 0 | F8: =IF(D8="East",1,0) -> 1 | G8: =IF(D8="West",1,0) -> 0 | H8: 46213.45 | I8: 10616 | J8: 0.122 | K8: 22 | L8: 85.2 | M8: 0.2 | N8: 1 | O8: 4.1 | P8: 806615.54 | Q8: 131364.62
A9: STR-1002 | B9: 45748 | C9: High Street | D9: East | E9: =IF(D9="South",1,0) -> 0 | F9: =IF(D9="East",1,0) -> 1 | G9: =IF(D9="West",1,0) -> 0 | H9: 68148.52 | I9: 8567 | J9: 0.127 | K9: 23 | L9: 95.6 | M9: 0.8 | N9: 0 | O9: 3.9 | P9: 850164.26 | Q9: 149262.75
A10: STR-1003 | B10: 45658 | C10: Airport | D10: North | E10: =IF(D10="South",1,0) -> 0 | F10: =IF(D10="East",1,0) -> 0 | G10: =IF(D10="West",1,0) -> 0 | H10: 71838.86 | I10: 10979 | J10: 0.215 | K10: 26 | L10: 88.6 | M10: 7.7 | N10: 1 | O10: 3.8 | P10: 930581.7 | Q10: 136207.98
A11: STR-1003 | B11: 45689 | C11: Airport | D11: North | E11: =IF(D11="South",1,0) -> 0 | F11: =IF(D11="East",1,0) -> 0 | G11: =IF(D11="West",1,0) -> 0 | H11: 68133.44 | I11: 9459 | J11: 0.22 | K11: 21 | L11: 85 | M11: 1.91 | N11: 0 | O11: 4.2 | P11: 779010.94 | Q11: 106328.09
A12: STR-1003 | B12: 45717 | C12: Airport | D12: North | E12: =IF(D12="South",1,0) -> 0 | F12: =IF(D12="East",1,0) -> 0 | G12: =IF(D12="West",1,0) -> 0 | H12: 34285.21 | I12: 9172 | J12: 0.213 | K12: 22 | L12: 88.3 | M12: 10.46 | N12: 1 | O12: 3.8 | P12: 723060.76 | Q12: 123131.24
A13: STR-1003 | B13: 45748 | C13: Airport | D13: North | E13: =IF(D13="South",1,0) -> 0 | F13: =IF(D13="East",1,0) -> 0 | G13: =IF(D13="West",1,0) -> 0 | H13: 67979.88 | I13: 11230 | J13: 0.002 | K13: 28 | L13: 85.3 | M13: 7.16 | N13: 0 | O13: 3.8 | P13: 910791.94 | Q13: 158891.28
... A321: STR-1080 | B321: 45748 | C321: Residential | D321: East | E321: =IF(D321="South",1,0) -> 0 | F321: =IF(D321="East",1,0) -> 1 | G321: =IF(D321="West",1,0) -> 0 | H321: 40553.11 | I321: 5317 | J321: 0.165 | K321: 17 | L321: 84.3 | M321: 11.82 | N321: 0 | O321: 4.1 | P321: 559660.84 | Q321: 71443.61

Sheet SRegression1
A1: SUMMARY OUTPUT
A3: Regression Statistics
A4: Multiple R | B4: 0.40895561
A5: R Square | B5: 0.16724469
A6: Adjusted R Square | B6: 0.16462596
A7: Standard Error | B7: 94846.034
A8: Observations | B8: 320
A10: ANOVA
B11: df | C11: SS | D11: MS | E11: F | F11: Significance F
A12: Regression | B12: 1 | C12: 5.7451371e+11 | D12: 5.7451371e+11 | E12: 63.864873 | F12: 2.4800615e-14
A13: Residual | B13: 318 | C13: 2.8606549e+12 | D13: 8.9957701e+09
A14: Total | B14: 319 | C14: 3.4351686e+12
B16: Coefficients | C16: Standard Error | D16: t Stat | E16: P-value | F16: Lower 95% | G16: Upper 95% | H16: Lower 95.0% | I16: Upper 95.0%
A17: Intercept | B17: 560777.35 | C17: 15906.906 | D17: 35.253703 | E17: 6.9528769e-112 | F17: 529481.27 | G17: 592073.42 | H17: 529481.27 | I17: 592073.42
A18: marketing_spend | B18: 2.1295753 | C18: 0.26647838 | D18: 7.9915501 | E18: 2.4800615e-14 | F18: 1.6052919 | G18: 2.6538587 | H18: 1.6052919 | I18: 2.6538587

Sheet SRegression2
A1: SUMMARY OUTPUT
A3: Regression Statistics
A4: Multiple R | B4: 0.85807071
A5: R Square | B5: 0.73628534
A6: Adjusted R Square | B6: 0.73545605
A7: Standard Error | B7: 53373.736
A8: Observations | B8: 320
A10: ANOVA
B11: df | C11: SS | D11: MS | E11: F | F11: Significance F
A12: Regression | B12: 1 | C12: 2.5292643e+12 | D12: 2.5292643e+12 | E12: 887.84878 | F12: 4.7503615e-94
A13: Residual | B13: 318 | C13: 9.0590432e+11 | D13: 2.8487557e+09
A14: Total | B14: 319 | C14: 3.4351686e+12
B16: Coefficients | C16: Standard Error | D16: t Stat | E16: P-value | F16: Lower 95% | G16: Upper 95% | H16: Lower 95.0% | I16: Upper 95.0%
A17: Intercept | B17: 446410.58 | C17: 8407.7383 | D17: 53.095205 | E17: 4.0862696e-160 | F17: 429868.76 | G17: 462952.4 | H17: 429868.76 | I17: 462952.4
A18: footfall | B18: 35.678031 | C18: 1.1973783 | D18: 29.796791 | E18: 4.7503615e-94 | F18: 33.322247 | G18: 38.033815 | H18: 33.322247 | I18: 38.033815

Sheet SRegression3
A1: SUMMARY OUTPUT
A3: Regression Statistics
A4: Multiple R | B4: 0.091052199
A5: R Square | B5: 0.008290503
A6: Adjusted R Square | B6: 0.0051719197
A7: Standard Error | B7: 103502.94
A8: Observations | B8: 320
A10: ANOVA
B11: df | C11: SS | D11: MS | E11: F | F11: Significance F
A12: Regression | B12: 1 | C12: 2.8479276e+10 | D12: 2.8479276e+10 | E12: 2.6584196 | F12: 0.10399305
A13: Residual | B13: 318 | C13: 3.4066893e+12 | D13: 1.071286e+10
A14: Total | B14: 319 | C14: 3.4351686e+12
B16: Coefficients | C16: Standard Error | D16: t Stat | E16: P-value | F16: Lower 95% | G16: Upper 95% | H16: Lower 95.0% | I16: Upper 95.0%
A17: Intercept | B17: 697835.63 | C17: 12035.419 | D17: 57.981832 | E17: 3.8725944e-171 | F17: 674156.52 | G17: 721514.74 | H17: 674156.52 | I17: 721514.74
A18: avg_discount_pct | B18: -138730.45 | C18: 85086.38 | D18: -1.6304661 | E18: 0.10399305 | F18: -306133.82 | G18: 28672.909 | H18: -306133.82 | I18: 28672.909

Sheet SRegression4
A1: SUMMARY OUTPUT
A3: Regression Statistics
A4: Multiple R | B4: 0.11452081
A5: R Square | B5: 0.013115016
A6: Adjusted R Square | B6: 0.010011604
A7: Standard Error | B7: 103250.87
A8: Observations | B8: 320
A10: ANOVA
B11: df | C11: SS | D11: MS | E11: F | F11: Significance F
A12: Regression | B12: 1 | C12: 4.5052291e+10 | D12: 4.5052291e+10 | E12: 4.2259991 | F12: 0.040625297
A13: Residual | B13: 318 | C13: 3.3901163e+12 | D13: 1.0660743e+10
A14: Total | B14: 319 | C14: 3.4351686e+12
B16: Coefficients | C16: Standard Error | D16: t Stat | E16: P-value | F16: Lower 95% | G16: Upper 95% | H16: Lower 95.0% | I16: Upper 95.0%
A17: Intercept | B17: 484814.26 | C17: 95428.021 | D17: 5.0804182 | E17: 6.4331365e-07 | F17: 297064.21 | G17: 672564.3 | H17: 297064.21 | I17: 672564.3
A18: inventory_availability_pct | B18: 2217.8319 | C18: 1078.8571 | D18: 2.0557235 | E18: 0.040625297 | F18: 95.232396 | G18: 4340.4315 | H18: 95.232396 | I18: 4340.4315

Sheet SRegression5
A1: SUMMARY OUTPUT
A3: Regression Statistics
A4: Multiple R | B4: 0.065137449
A5: R Square | B5: 0.0042428873
A6: Adjusted R Square | B6: 0.0011115756
A7: Standard Error | B7: 103713.95
A8: Observations | B8: 320
A10: ANOVA
B11: df | C11: SS | D11: MS | E11: F | F11: Significance F
A12: Regression | B12: 1 | C12: 1.4575033e+10 | D12: 1.4575033e+10 | E12: 1.3549872 | F12: 0.24528073
A13: Residual | B13: 318 | C13: 3.4205936e+12 | D13: 1.0756584e+10
A14: Total | B14: 319 | C14: 3.4351686e+12
B16: Coefficients | C16: Standard Error | D16: t Stat | E16: P-value | F16: Lower 95% | G16: Upper 95% | H16: Lower 95.0% | I16: Upper 95.0%
A17: Intercept | B17: 648445.21 | C17: 28249.486 | D17: 22.954231 | E17: 1.8890628e-69 | F17: 592865.7 | G17: 704024.72 | H17: 592865.7 | I17: 704024.72
A18: customer_rating | B18: 8410.5531 | C18: 7225.3179 | D18: 1.1640392 | E18: 0.24528073 | F18: -5804.9127 | G18: 22626.019 | H18: -5804.9127 | I18: 22626.019

Sheet SR Summary
B1: Regression equation | C1: R-squared | D1: Coefficient | E1: P-value
A2: marketing_spend | B2: =SRegression1!B17 -> 560777.35 | C2: =SRegression1!B5 -> 0.16724469 | D2: =SRegression1!B18 -> 2.1295753 | E2: =SRegression1!E18 -> 2.4800615e-14
A3: footfall | B3: =SRegression2!B17 -> 446410.58 | C3: =SRegression2!B5 -> 0.73628534 | D3: =SRegression2!B18 -> 35.678031 | E3: =SRegression2!E18 -> 4.7503615e-94
A4: avg_discount_pct | B4: =SRegression3!B17 -> 697835.63 | C4: =SRegression3!B5 -> 0.008290503 | D4: =SRegression3!B18 -> -138730.45 | E4: =SRegression3!E18 -> 0.10399305
A5: inventory_availability_pct | B5: =SRegression4!B17 -> 484814.26 | C5: =SRegression4!B5 -> 0.013115016 | D5: =SRegression4!B18 -> 2217.8319 | E5: =SRegression4!E18 -> 0.040625297
A6: customer_rating | B6: =SRegression5!B17 -> 648445.21 | C6: =SRegression5!B5 -> 0.0042428873 | D6: =SRegression5!B18 -> 8410.5531 | E6: =SRegression5!E18 -> 0.24528073
A10: Independent Variable | B10: Business Interpretation | C10: Whether the Variable Appears Useful?
A11: marketing_spend | B11: Marketing spend has a positive relationship with monthly sales. The coefficient (2.13) indicates that every additional ₹1 spent on marketing is associated with an increase of approximately ₹2.13 in monthly sales. Although the model explains only 16.72% of the variation in sales, the very small p-value indicates the relationship is statistically significant. | C11: Yes. The variable is statistically significant (p < 0.05) and has a positive effect on sales, making it a useful predictor.
A12: footfall | B12: Footfall has a strong positive relationship with monthly sales. The coefficient (35.68) suggests that each additional customer visiting the store is associated with an increase of approximately ₹35.68 in monthly sales. The model explains 73.63% of the variation in sales, indicating excellent predictive power. | C12: Yes. This is the strongest predictor among the simple regression models. It has a high R² and an extremely small p-value, making it highly useful for predicting monthly sales.
A13: avg_discount_pct | B13: Average discount percentage has a negative relationship with monthly sales. The negative coefficient (-138,730.45) suggests that increasing discounts may reduce monthly sales in this dataset. However, the relationship is not statistically significant. | C13: No. Since the p-value (0.104) is greater than 0.05 and the R² is only 0.83%, this variable should not be interpreted as having a meaningful effect on monthly sales.
A14: inventory_availability_pct | B14: Inventory availability has a positive relationship with monthly sales. The coefficient (2,217.83) indicates that better inventory availability is associated with higher monthly sales. However, the model explains only 1.31% of the variation in sales. | C14: Partially. The variable is statistically significant (p = 0.0406), but its very low R² indicates that, by itself, it is a weak predictor of monthly sales. It may become more useful when combined with other variables in a multiple regression model.
A15: customer_rating | B15: Customer rating has a positive relationship with monthly sales. Higher customer ratings are associated with higher sales, but the relationship is weak and not statistically significant. | C15: No. The p-value (0.245) is greater than 0.05 and the R² is only 0.42%, indicating that customer rating alone is not a reliable predictor of monthly sales in this dataset.

Sheet Multiple Regression
A1: SUMMARY OUTPUT
A3: Regression Statistics
A4: Multiple R | B4: 0.88731043
A5: R Square | B5: 0.7873198
A6: Adjusted R Square | B6: 0.7846191
A7: Standard Error | B7: 48159.535
A8: Observations | B8: 320
A10: ANOVA
B11: df | C11: SS | D11: MS | E11: F | F11: Significance F
A12: Regression | B12: 4 | C12: 2.7045763e+12 | D12: 6.7614407e+11 | E12: 291.52424 | F12: 1.6365614e-104
A13: Residual | B13: 315 | C13: 7.3059235e+11 | D13: 2.3193408e+09
A14: Total | B14: 319 | C14: 3.4351686e+12
B16: Coefficients | C16: Standard Error | D16: t Stat | E16: P-value | F16: Lower 95% | G16: Upper 95% | H16: Lower 95.0% | I16: Upper 95.0%
A17: Intercept | B17: 404245.39 | C17: 11377.482 | D17: 35.530305 | E17: 3.2242802e-112 | F17: 381859.93 | G17: 426630.85 | H17: 381859.93 | I17: 426630.85
A18: West Dummy | B18: 10436.877 | C18: 5958.3797 | D18: 1.7516301 | E18: 0.080810622 | F18: -1286.3753 | G18: 22160.129 | H18: -1286.3753 | I18: 22160.129
A19: marketing_spend | B19: 1.1375687 | C19: 0.13948288 | D19: 8.1556154 | E19: 8.3459471e-15 | F19: 0.86313286 | G19: 1.4120045 | H19: 0.86313286 | I19: 1.4120045
A20: footfall | B20: 33.564798 | C20: 1.1121426 | D20: 30.1803 | E20: 5.9083408e-95 | F20: 31.376631 | G20: 35.752965 | H20: 31.376631 | I20: 35.752965
A21: avg_discount_pct | B21: -88560.591 | C21: 39654.766 | D21: -2.23329 | E21: 0.026231835 | F21: -166582.27 | G21: -10538.906 | H21: -166582.27 | I21: -10538.906
A25: RESIDUAL OUTPUT
A27: Observation | B27: Predicted monthly_sales | C27: Residuals | D27: Standard Residuals
A28: 1 | B28: 759253.25 | C28: -100420.63 | D28: -2.0983634
A29: 2 | B29: 724088.89 | C29: -89652.887 | D29: -1.8733635
A30: 3 | B30: 766507.94 | C30: -87785.883 | D30: -1.8343511
A31: 4 | B31: 772897.72 | C31: -113977.42 | D31: -2.3816426
A32: 5 | B32: 759236.59 | C32: -17895.155 | D32: -0.37393252
A33: 6 | B33: 796720.31 | C33: -34884.97 | D33: -0.72894731
A34: 7 | B34: 802335.87 | C34: 4279.672 | D34: 0.089426919
A35: 8 | B35: 758071.44 | C35: 92092.817 | D35: 1.9243477
A36: 9 | B36: 835434.42 | C36: 95147.281 | D36: 1.988173
A37: 10 | B37: 779757.95 | C37: -747.01342 | D37: -0.015609399
A38: 11 | B38: 732240.09 | C38: -9179.3334 | D38: -0.19180897
A39: 12 | B39: 858332.73 | C39: 52459.206 | D39: 1.096174
... A347: 320 | B347: 614228.87 | C347: -54568.032 | D347: -1.1402395

Sheet MR Visuals

Sheet MR Summary
A1: Multiple Regression Equation
A3: 1. Intercept
A5: Intercept | B5: ='Multiple Regression'!B17 -> 404245.39
A7: Interpretation:
A8: The intercept represents the estimated monthly sales when all independent variables are equal to zero and the store belongs to the reference region (the region for which the dummy variable equals 0). While this situation is unlikely in practice, the intercept provides the baseline value for the regression model.
A12: 2. Coefficients
A14: Variable | B14: Coefficient | C14: Interpretation
A15: West Dummy | B15: 10436.88 | C15: Stores in the West region are predicted to have approximately ₹10,437 higher monthly sales than stores in the reference region, after controlling for the other variables. However, this difference is not statistically significant.
A16: Marketing Spend | B16: 1.1376 | C16: Every additional ₹1 spent on marketing is associated with an increase of approximately ₹1.14 in monthly sales, holding other variables constant.
A17: Footfall | B17: 33.5648 | C17: Every additional customer visiting the store is associated with an increase of approximately ₹33.56 in monthly sales, holding other variables constant.
A18: Average Discount % | B18: −88,560.59 | C18: A one-unit increase in the average discount percentage is associated with a decrease of approximately ₹88,561 in monthly sales, after controlling for the other variables.
A21: 3. R-squared (R²)
A23: R² | B23: ='Multiple Regression'!B5 -> 0.7873198
A25: Interpretation:
A26: The regression model explains 78.73% of the variation in monthly sales, indicating that the selected independent variables provide a strong explanation of differences in monthly sales across stores.
A30: 4. P-values
A32: Variable | B32: P-value | C32: Interpretation
A33: West Dummy | B33: ='Multiple Regression'!E18 -> 0.080810622 | C33: Not statistically significant (p > 0.05).
A34: Marketing Spend | B34: ='Multiple Regression'!E19 -> 8.3459471e-15 | C34: Highly statistically significant.
A35: Footfall | B35: ='Multiple Regression'!E20 -> 5.9083408e-95 | C35: Extremely statistically significant.
A36: Average Discount % | B36: ='Multiple Regression'!E21 -> 0.026231835 | C36: Statistically significant (p < 0.05).
A39: 5. Direction of Relationship
A41: Variable | B41: Relationship
A42: Marketing Spend | B42: Positive
A43: Footfall | B43: Positive
A44: Average Discount % | B44: Negative
A45: West Dummy | B45: Positive, but statistically insignificant
A48: 6. Business Meaning of Important Variables
A50: Marketing Spend
A51: Marketing expenditure has a positive and statistically significant impact on monthly sales. Increasing investment in marketing is associated with higher sales revenue, making marketing an important driver of store performance.
A53: Footfall
A54: Footfall is the strongest predictor in the model. Stores with higher customer traffic consistently generate higher monthly sales, indicating that attracting more customers should be a key business objective.
A56: Average Discount Percentage
A57: Average discount percentage has a statistically significant negative relationship with monthly sales. This suggests that larger discounts may reduce overall sales revenue, possibly because excessive discounting lowers average transaction values or reflects weaker sales performance.
A59: 7. Variables That Are Statistically Weak or Difficult to Interpret
A61: West Dummy
A62: P-value | B62: ='Multiple Regression'!E18 -> 0.080810622 | C62: (> 0.05)
A63: Not statistically significant.
A65: Although the coefficient is positive, there is insufficient statistical evidence to conclude that stores in the West region perform differently from stores in the reference region after accounting for marketing spend, footfall, and discount percentage. Therefore, this variable should be interpreted cautiously and should not be considered a strong predictor of monthly sales.
